ggtoolset/ConfigReader.py
ggtoolset/InitializeML.py
ggtoolset/Utils.py
ggtoolset/__init__.py
ggtoolset-0.1.10.dist-info/LICENSE
ggtoolset-0.1.10.dist-info/METADATA
ggtoolset-0.1.10.dist-info/WHEEL
ggtoolset-0.1.10.dist-info/top_level.txt
ggtoolset-0.1.10.dist-info/RECORD
