Metadata-Version: 2.1
Name: ggtoolset
Version: 0.1.10
Summary: everday utilities
Home-page: https://github.com/
Author: gg61021277
Author-email: gg61021277@gmail.com
Classifier: Programming Language :: Python :: 3
Classifier: License :: OSI Approved :: MIT License
Classifier: Operating System :: OS Independent
Requires-Python: >=3.6
License-File: LICENSE
Requires-Dist: python-box>=5.0.0
